quantalent/__init__.py
quantalent/llm/__init__.py
quantalent/llm/base.py
quantalent/llm/factory.py
quantalent/llm/ollama_provider.py
quantalent/llm/openai_provider.py
quantalent/search/__init__.py
quantalent/search/base.py
quantalent/search/brave_provider.py
quantalent/search/factory.py
quantalent/utils/__init__.py
quantalent/utils/_webutils.py
quantalent-0.1.3.dist-info/METADATA
quantalent-0.1.3.dist-info/WHEEL
quantalent-0.1.3.dist-info/RECORD
