Metadata-Version: 2.3
Name: quantalent
Version: 0.1.3
Summary: 
Author: Stefan Auw Yang
Author-email: stefan_ay@yahoo.com
Requires-Python: >=3.13,<4.0
Classifier: Programming Language :: Python :: 3
Classifier: Programming Language :: Python :: 3.13
Requires-Dist: beautifulsoup4 (>=4.13.3,<5.0.0)
Requires-Dist: brave-search-python-client (>=0.4.11,<0.5.0)
Requires-Dist: openai (>=1.70.0,<2.0.0)
Requires-Dist: requests (>=2.32.3,<3.0.0)
Requires-Dist: setuptools (>=78.1.0,<79.0.0)
